deepface_cv2/DeepFace.py
deepface_cv2/FaceDetector.py
deepface_cv2/__init__.py
deepface_cv2/preprocess.py
deepface_cv2/models/ArcFace.py
deepface_cv2/models/DeepID.py
deepface_cv2/models/FaceNet.py
deepface_cv2/models/FaceNet512.py
deepface_cv2/models/OpenFace.py
deepface_cv2/models/VGGFace.py
deepface_cv2/models/__init__.py
deepface_cv2-0.0.1.dist-info/LICENSE
deepface_cv2-0.0.1.dist-info/METADATA
deepface_cv2-0.0.1.dist-info/WHEEL
deepface_cv2-0.0.1.dist-info/top_level.txt
deepface_cv2-0.0.1.dist-info/RECORD
