Metadata-Version: 2.1
Name: deepface-cv2
Version: 0.0.1
Summary: deepface with opencv, no need for tensorflow/keras
Home-page: https://github.com/linxiaohui/deepface_cv2
Author: Lin Xiao Hui
Author-email: llinxiaohui@126.com
License: UNKNOWN
Platform: UNKNOWN
Classifier: Programming Language :: Python :: 3
Classifier: License :: OSI Approved :: MIT License
Classifier: Operating System :: OS Independent
Requires-Python: >=3.6
License-File: LICENSE
Requires-Dist: opencv-python
